oligo/__init__.py
oligo/exception.py
oligo/asyncio/__init__.py
oligo/asyncio/asynciber.py
oligo/requests/__init__.py
oligo/requests/iber.py
oligo-2.1.2.dist-info/licenses/LICENSE
tests/__init__.py
tests/test_aioiber.py
tests/test_exception.py
tests/test_iber.py
oligo-2.1.2.dist-info/METADATA
oligo-2.1.2.dist-info/WHEEL
oligo-2.1.2.dist-info/top_level.txt
oligo-2.1.2.dist-info/RECORD
