Metadata-Version: 2.4
Name: oligo
Version: 2.1.2
Summary: UNOFFICIAL Python client for i-DE
Home-page: https://github.com/hectorespert/python-oligo
Author: hectorespert
Author-email: hectorespertpardo@gmail.com
Classifier: Programming Language :: Python :: 3
Classifier: License :: OSI Approved :: MIT License
Classifier: Operating System :: OS Independent
Requires-Python: >=3.6
License-File: LICENSE
Requires-Dist: deprecated
Provides-Extra: requests
Requires-Dist: requests; extra == "requests"
Provides-Extra: asyncio
Requires-Dist: aiohttp; extra == "asyncio"
Dynamic: author
Dynamic: author-email
Dynamic: classifier
Dynamic: description
Dynamic: description-content-type
Dynamic: home-page
Dynamic: license-file
Dynamic: provides-extra
Dynamic: requires-dist
Dynamic: requires-python
Dynamic: summary
